{"components_index.md":"b350c18d","feelings_a-upload.md":"39faef76","feelings_echarts-wordcloud.md":"2f59b785","feelings_el-date-picker.md":"bf5ea7af","feelings_js-lazy-load.md":"3b27e248","feelings_vue3-waterfall-flow.md":"57647d41","guide_docker-compose.md":"9b163ce8","guide_docker-github.md":"38cd40a8","guide_flutter-const.md":"162bf0c6","guide_flutter-mall.md":"5003923e","guide_flutter-weiget.md":"9705b805","guide_vue3-tinymce.md":"165ac382","guide_vue3-upgrade.md":"f45db05e","index.md":"7879f6e6","node_git-npm.md":"92dc90aa","tale_hexo-create.md":"b77bb1a1","tale_hualang.md":"a4a1fd25","tale_p1-zongjie.md":"0617fb4f","widgets_index.md":"81a45ab1"}
